[{"id": "41XqX", "meters": "50", "price": "315000", "rooms": "3", "dealer": "HOME-TRADER", "title": "3 oddzielne pokoje, Os. Skarpa, przy samym w\u0105wozie", "location": ["Lublin", "Czuby"], "district": "Czuby"}, {"id": "41Ssp", "meters": "51.45", "price": "315000", "rooms": "3", "dealer": "VISUMNIERUCHOMO\u015aCI", "title": "2-3 Pokoje, Nowe Budownictwo, Nowy \u015awiat", "location": ["Lublin", "Dziesi\u0105ta"], "district": "Dziesi\u0105ta"}, {"id": "3Ymqo", "meters": "47.04", "price": "365000", "rooms": "2", "dealer": "4tepi\u0119tro", "title": "Gotowe! Czuby, umeblowane, 2 pokoje + ogr\u00f3dek", "location": ["Lublin", "Czuby"], "district": "Czuby"}, {"id": "3SUUc", "meters": "98", "price": "510000", "rooms": "4", "dealer": "LubelskieMieszkania", "title": "Dwupoziomowe mieszkanie na os. Por\u0119ba", "location": ["Lublin", "Czuby"], "district": "Czuby"}, {"id": "3STwy", "meters": "61.30", "price": "315695", "rooms": "3", "dealer": "ExpressHouse", "title": "Mieszkanie, 61,30 m\u00b2, Lublin", "location": ["Lublin", "Felin"], "district": "Felin"}, {"id": "3STwC", "meters": "51.36", "price": "264504", "rooms": "2", "dealer": "ExpressHouse", "title": "Mieszkanie, 51,36 m\u00b2, Lublin", "location": ["Lublin", "Felin"], "district": "Felin"}, {"id": "3STwq", "meters": "64.98", "price": "337896", "rooms": "3", "dealer": "ExpressHouse", "title": "Mieszkanie, 64,98 m\u00b2, Lublin", "location": ["Lublin", "Felin"], "district": "Felin"}, {"id": "3SSni", "meters": "35.87", "price": "215220", "rooms": "2", "dealer": "CLIVUSNieruchomo\u015bci", "title": "Lublin Okol. Centrum Ostatnie wolne M poni\u017cej 40m2", "location": ["Lublin", "Ko\u015bminek"], "district": "Ko\u015bminek"}, {"id": "3SMP2", "meters": "70.90", "price": "369000", "rooms": "3", "dealer": "BiuroNieruchomo\u015bciKWADRAT", "title": "3 Pokoje , Konstantyn\u00f3w , Od Zaraz !!!", "location": ["Lublin", "Konstantyn\u00f3w"], "district": "Konstantyn\u00f3w"}, {"id": "3SIhu", "meters": "69", "price": "449000", "rooms": "2", "dealer": "LubelskieMieszkania", "title": "Centrum miasta, 69 m2,wysoki stand. z m. postojowy", "location": ["Lublin", "\u015ar\u00f3dmie\u015bcie"], "district": "\u015ar\u00f3dmie\u015bcie"}, {"id": "3SIaQ", "meters": "117", "price": "520000", "rooms": "5", "dealer": "LubelskieMieszkania", "title": "Wysoki standard, 2 poziomy, 5pok.,2 \u0142azienki 117m2", "location": ["Lublin", "S\u0142awinek"], "district": "S\u0142awinek"}, {"id": "3SDuk", "meters": "71", "price": "360000", "rooms": "3", "dealer": "BiuroNieruchomo\u015bciFACTOR", "title": "\u015acis\u0142e Centrum, Przestronne Mieszkanie", "location": ["Lublin", "\u015ar\u00f3dmie\u015bcie"], "district": "\u015ar\u00f3dmie\u015bcie"}, {"id": "3SDug", "meters": "41", "price": "240000", "rooms": "2", "dealer": "BiuroNieruchomo\u015bciFACTOR", "title": "\u015acis\u0142e Centrum, Przestronne Mieszkanie", "location": ["Lublin", "\u015ar\u00f3dmie\u015bcie"], "district": "\u015ar\u00f3dmie\u015bcie"}, {"id": "3SsO8", "meters": "68", "price": "350000", "rooms": "4", "dealer": "PrestigeBroker", "title": "Mieszkanie, 68 m\u00b2, Lublin", "location": ["Lublin", "lubelskie"], "district": "lubelskie"}, {"id": "3Ss2o", "meters": "69.64", "price": "395000", "rooms": "3", "dealer": "BiuroNieruchomo\u015bciKWADRAT", "title": "Mieszkanie 69,64 m2, \u015ar\u00f3dmie\u015bcie , 3 pok.", "location": ["Lublin", "\u015ar\u00f3dmie\u015bcie"], "district": "\u015ar\u00f3dmie\u015bcie"}, {"id": "3Snhm", "meters": "72.20", "price": "399500", "rooms": "4", "dealer": "WMNieruchomo\u015bci", "title": "Czech\u00f3w 72 mkw, 4 pok. U. Medyczny!!!", "location": ["Lublin", "Czech\u00f3w"], "district": "Czech\u00f3w"}, {"id": "3SkVY", "meters": "48.70", "price": "277590", "rooms": "2", "dealer": "ExpertNieruchomo\u015bci", "title": "Mieszkanie 48,70 mkw 2P+K, Lublin", "location": ["Lublin", "Wrotk\u00f3w"], "district": "Wrotk\u00f3w"}, {"id": "3SiSA", "meters": "43.51", "price": "256709", "rooms": "2", "dealer": "ExpertNieruchomo\u015bci", "title": "Mieszkanie 43,51 mkw Lublin 2P+ Ak", "location": ["Lublin", "Wrotk\u00f3w"], "district": "Wrotk\u00f3w"}, {"id": "3ShZm", "meters": "35.87", "price": "215220", "rooms": "2", "dealer": "CLIVUSNieruchomo\u015bci", "title": "Lublin Ostatnie mieszkania do 40 m2 ! Idealne*****", "location": ["Lublin", "Ko\u015bminek"], "district": "Ko\u015bminek"}, {"id": "3Sax6", "meters": "46.51", "price": "274409", "rooms": "3", "dealer": "CLIVUSNieruchomo\u015bci", "title": "Lublin ostatnie wolne mieszkania 3P lub 2P Okazja", "location": ["Lublin", "Bronowice"], "district": "Bronowice"}, {"id": "3S8VQ", "meters": "57", "price": "390000", "rooms": "3", "dealer": "CLIVUSNieruchomo\u015bci", "title": "Lublin, Czyby", "location": ["Lublin", "Czuby"], "district": "Czuby"}, {"id": "3S5d2", "meters": "29.50", "price": "171100", "rooms": "2", "dealer": "KancelariaFinansowaKrzysztofNieznaj", "title": "Kawalerka w atrakcyjnej cenie", "location": ["Lublin", "Dziesi\u0105ta"], "district": "Dziesi\u0105ta"}, {"id": "3S1f6", "meters": "51", "price": "380000", "rooms": "2", "dealer": "OnestoBroker", "title": "Mieszkanie deweloperskie 52m\u00b2 ul. Pana Balcera 6B", "location": ["Lublin", "LSM"], "district": "LSM"}, {"id": "3RV2Q", "meters": "169", "price": "460000", "rooms": "5", "dealer": "BWBROKERBiuroNieruchomo\u015bciBart\u0142omiejWolak", "title": "Lokal mieszkalny z ogr\u00f3dkiem - bezczynszowy", "location": ["Lublin", "Bronowice"], "district": "Bronowice"}, {"id": "3MeL2", "meters": "56.78", "price": "317400.20", "rooms": "3", "dealer": "Nieruchomo\u015bciLalakPropertiesSpzo.o.SKA", "title": "Nowe Mieszkania III Etap Diamentowe Wzg\u00f3rze", "location": ["Lublin", "Wrotk\u00f3w"], "district": "Wrotk\u00f3w"}, {"id": "3RHPa", "meters": "68.37", "price": "429000", "rooms": "4", "dealer": "BIURONIERUCHOMO\u015aCIANMA", "title": "Mieszkanie w nowym bloku, ok. Uniwers. Medycznego", "location": ["Lublin", "lubelskie"], "district": "lubelskie"}, {"id": "3REu4", "meters": "58", "price": "335000", "rooms": "4", "dealer": "P\u00f3\u0142nocNieruchomo\u015bciFranczyza", "title": "Mieszkanie po generalnym remoncie na Czechowie", "location": ["Lublin", "Czech\u00f3w"], "district": "Czech\u00f3w"}]